{"timestamp":"2025-01-06T01:33:23.546Z","sourceFile":"src/_data/indexes/moz-top-500.json","data":[{"url":"www.blogger.com","hosted_by":"Google Inc.","green":true,"hosted_by_id":595,"modified":"2025-01-06T01:32:31.396613"},{"url":"youtube.com","hosted_by":"Google Inc.","green":true,"hosted_by_id":595,"modified":"2025-01-06T01:32:31.443620"},{"url":"www.google.com","hosted_by":"Google Inc.","green":true,"hosted_by_id":595,"modified":"2025-01-06T01:32:31.495928"},{"url":"wordpress.org","hosted_by":null,"green":false,"hosted_by_id":null,"modified":"2025-01-06T01:32:31.562025"},{"url":"cloudflare.com","hosted_by":"Cloudflare","green":true,"hosted_by_id":779,"modified":"2025-01-06T01:32:31.595279"},{"url":"googleusercontent.com","hosted_by":"Google Inc.","green":true,"hosted_by_id":595,"modified":"2025-01-06T01:32:31.640196"},{"url":"apple.com","hosted_by":null,"green":false,"hosted_by_id":null,"modified":"2025-01-06T01:32:32.168222"},{"url":"linkedin.com","hosted_by":"Microsoft Azure","green":true,"hosted_by_id":1091,"modified":"2025-01-06T01:32:32.186642"},{"url":"support.google.com","hosted_by":"Google Inc.","green":true,"hosted_by_id":595,"modified":"2025-01-06T01:32:32.235372"},{"url":"youtu.be","hosted_by":"Google Inc.","green":true,"hosted_by_id":595,"modified":"2025-01-06T01:32:32.275158"},{"url":"microsoft.com","hosted_by":"Microsoft Azure","green":true,"hosted_by_id":1091,"modified":"2025-01-06T01:32:32.354511"},{"url":"docs.google.com","hosted_by":"Google Inc.","green":true,"hosted_by_id":595,"modified":"2025-01-06T01:32:32.398745"},{"url":"whatsapp.com","hosted_by":"Facebook","green":true,"hosted_by_id":475,"modified":"2025-01-06T01:32:32.433526"},{"url":"maps.google.com","hosted_by":"Google Inc.","green":true,"hosted_by_id":595,"modified":"2025-01-06T01:32:32.480920"},{"url":"play.google.com","hosted_by":"Google Inc.","green":true,"hosted_by_id":595,"modified":"2025-01-06T01:32:32.527283"},{"url":"plus.google.com","hosted_by":"Google Inc.","green":true,"hosted_by_id":595,"modified":"2025-01-06T01:32:32.571393"},{"url":"en.wikipedia.org","hosted_by":null,"green":false,"hosted_by_id":null,"modified":"2025-01-06T01:32:32.598287"},{"url":"europa.eu","hosted_by":null,"green":false,"hosted_by_id":null,"modified":"2025-01-06T01:32:33.126000"},{"url":"policies.google.com","hosted_by":"Google Inc.","green":true,"hosted_by_id":595,"modified":"2025-01-06T01:32:33.172220"},{"url":"mozilla.org","hosted_by":"Google Inc.","green":true,"hosted_by_id":595,"modified":"2025-01-06T01:32:33.261499"},{"url":"drive.google.com","hosted_by":"Google Inc.","green":true,"hosted_by_id":595,"modified":"2025-01-06T01:32:32.046271"},{"url":"t.me","hosted_by":null,"green":false,"hosted_by_id":null,"modified":"2025-01-06T01:32:32.130651"},{"url":"accounts.google.com","hosted_by":"Google Inc.","green":true,"hosted_by_id":595,"modified":"2025-01-06T01:32:32.166253"},{"url":"vk.com","hosted_by":null,"green":false,"hosted_by_id":null,"modified":"2025-01-06T01:32:32.715845"},{"url":"tiktok.com","hosted_by":null,"green":false,"hosted_by_id":null,"modified":"2025-01-06T01:32:33.041746"},{"url":"vimeo.com","hosted_by":"Cloudflare","green":true,"hosted_by_id":779,"modified":"2025-01-06T01:32:33.109145"},{"url":"wa.me","hosted_by":"Facebook","green":true,"hosted_by_id":475,"modified":"2025-01-06T01:32:33.138922"},{"url":"adobe.com","hosted_by":null,"green":false,"hosted_by_id":null,"modified":"2025-01-06T01:32:33.414920"},{"url":"pt.wikipedia.org","hosted_by":null,"green":false,"hosted_by_id":null,"modified":"2025-01-06T01:32:33.490958"},{"url":"draft.blogger.com","hosted_by":"Google Inc.","green":true,"hosted_by_id":595,"modified":"2025-01-06T01:32:33.772961"},{"url":"istockphoto.com","hosted_by":null,"green":false,"hosted_by_id":null,"modified":"2025-01-06T01:32:33.840915"},{"url":"es.wikipedia.org","hosted_by":null,"green":false,"hosted_by_id":null,"modified":"2025-01-06T01:32:33.920211"},{"url":"facebook.com","hosted_by":"Facebook","green":true,"hosted_by_id":475,"modified":"2025-01-06T01:32:33.943651"},{"url":"sites.google.com","hosted_by":"Google Inc.","green":true,"hosted_by_id":595,"modified":"2025-01-06T01:32:33.972768"},{"url":"bp.blogspot.com","hosted_by":null,"green":false,"hosted_by_id":null,"modified":"2025-01-06T01:32:33.987849"},{"url":"amazon.com","hosted_by":"Amazon Web Services","green":true,"hosted_by_id":697,"modified":"2025-01-06T01:32:34.063226"},{"url":"github.com","hosted_by":null,"green":false,"hosted_by_id":null,"modified":"2025-01-06T01:32:34.140498"},{"url":"paypal.com","hosted_by":null,"green":false,"hosted_by_id":null,"modified":"2025-01-06T01:32:34.227735"},{"url":"nih.gov","hosted_by":null,"green":false,"hosted_by_id":null,"modified":"2025-01-06T01:32:34.804282"},{"url":"brandbucket.com","hosted_by":"Cloudflare","green":true,"hosted_by_id":779,"modified":"2025-01-06T01:32:34.834758"},{"url":"bbc.co.uk","hosted_by":null,"green":false,"hosted_by_id":null,"modified":"2025-01-06T01:32:33.274716"},{"url":"tools.google.com","hosted_by":"Google Inc.","green":true,"hosted_by_id":595,"modified":"2025-01-06T01:32:33.311731"},{"url":"developers.google.com","hosted_by":"Google Inc.","green":true,"hosted_by_id":595,"modified":"2025-01-06T01:32:33.352512"},{"url":"forms.gle","hosted_by":null,"green":false,"hosted_by_id":null,"modified":"2025-01-06T01:32:33.626357"},{"url":"abril.com.br","hosted_by":null,"green":false,"hosted_by_id":null,"modified":"2025-01-06T01:32:33.949599"},{"url":"dailymotion.com","hosted_by":null,"green":false,"hosted_by_id":null,"modified":"2025-01-06T01:32:34.508902"},{"url":"goo.gl","hosted_by":"Google Inc.","green":true,"hosted_by_id":595,"modified":"2025-01-06T01:32:34.541105"},{"url":"google.es","hosted_by":"Google Inc.","green":true,"hosted_by_id":595,"modified":"2025-01-06T01:32:34.583080"},{"url":"wikimedia.org","hosted_by":null,"green":false,"hosted_by_id":null,"modified":"2025-01-06T01:32:34.607972"},{"url":"opera.com","hosted_by":null,"green":false,"hosted_by_id":null,"modified":"2025-01-06T01:32:35.166372"},{"url":"news.google.com","hosted_by":"Google Inc.","green":true,"hosted_by_id":595,"modified":"2025-01-06T01:32:35.204897"},{"url":"medium.com","hosted_by":"Cloudflare","green":true,"hosted_by_id":779,"modified":"2025-01-06T01:32:35.232254"},{"url":"googleblog.com","hosted_by":"Google Inc.","green":true,"hosted_by_id":595,"modified":"2025-01-06T01:32:35.270034"},{"url":"google.com.br","hosted_by":"Google Inc.","green":true,"hosted_by_id":595,"modified":"2025-01-06T01:32:35.305793"},{"url":"files.wordpress.com","hosted_by":null,"green":false,"hosted_by_id":null,"modified":"2025-01-06T01:32:35.638106"},{"url":"gravatar.com","hosted_by":null,"green":false,"hosted_by_id":null,"modified":"2025-01-06T01:32:35.951303"},{"url":"dropbox.com","hosted_by":null,"green":false,"hosted_by_id":null,"modified":"2025-01-06T01:32:36.483266"},{"url":"dan.com","hosted_by":null,"green":false,"hosted_by_id":null,"modified":"2025-01-06T01:32:36.800109"},{"url":"mail.ru","hosted_by":null,"green":false,"hosted_by_id":null,"modified":"2025-01-06T01:32:37.075884"},{"url":"cpanel.net","hosted_by":null,"green":false,"hosted_by_id":null,"modified":"2025-01-06T01:32:37.651976"},{"url":"feedburner.com","hosted_by":"Google Inc.","green":true,"hosted_by_id":595,"modified":"2025-01-06T01:32:33.682680"},{"url":"cnn.com","hosted_by":null,"green":false,"hosted_by_id":null,"modified":"2025-01-06T01:32:33.956856"},{"url":"w3.org","hosted_by":"Cloudflare","green":true,"hosted_by_id":779,"modified":"2025-01-06T01:32:33.985760"},{"url":"gstatic.com","hosted_by":"Google Inc.","green":true,"hosted_by_id":595,"modified":"2025-01-06T01:32:34.018979"},{"url":"www.weebly.com","hosted_by":null,"green":false,"hosted_by_id":null,"modified":"2025-01-06T01:32:34.364234"},{"url":"theguardian.com","hosted_by":null,"green":false,"hosted_by_id":null,"modified":"2025-01-06T01:32:34.391495"},{"url":"fr.wikipedia.org","hosted_by":null,"green":false,"hosted_by_id":null,"modified":"2025-01-06T01:32:34.564487"},{"url":"uol.com.br","hosted_by":null,"green":false,"hosted_by_id":null,"modified":"2025-01-06T01:32:35.075633"},{"url":"nytimes.com","hosted_by":null,"green":false,"hosted_by_id":null,"modified":"2025-01-06T01:32:35.399428"},{"url":"ok.ru","hosted_by":null,"green":false,"hosted_by_id":null,"modified":"2025-01-06T01:32:35.677744"},{"url":"imdb.com","hosted_by":"Amazon Web Services","green":true,"hosted_by_id":697,"modified":"2025-01-06T01:32:35.744469"},{"url":"google.de","hosted_by":"Google Inc.","green":true,"hosted_by_id":595,"modified":"2025-01-06T01:32:35.782728"},{"url":"www.yahoo.com","hosted_by":null,"green":false,"hosted_by_id":null,"modified":"2025-01-06T01:32:35.808195"},{"url":"who.int","hosted_by":null,"green":false,"hosted_by_id":null,"modified":"2025-01-06T01:32:36.131932"},{"url":"line.me","hosted_by":null,"green":false,"hosted_by_id":null,"modified":"2025-01-06T01:32:36.699721"},{"url":"globo.com","hosted_by":null,"green":false,"hosted_by_id":null,"modified":"2025-01-06T01:32:37.271530"},{"url":"netvibes.com","hosted_by":null,"green":false,"hosted_by_id":null,"modified":"2025-01-06T01:32:37.994134"},{"url":"shopify.com","hosted_by":"Cloudflare","green":true,"hosted_by_id":779,"modified":"2025-01-06T01:32:38.338378"},{"url":"myspace.com","hosted_by":"Google Inc.","green":true,"hosted_by_id":595,"modified":"2025-01-06T01:32:38.409032"},{"url":"x.com","hosted_by":null,"green":false,"hosted_by_id":null,"modified":"2025-01-06T01:32:38.493076"},{"url":"nginx.com","hosted_by":null,"green":false,"hosted_by_id":null,"modified":"2025-01-06T01:32:34.944524"},{"url":"ovh.com","hosted_by":"OVHcloud","green":true,"hosted_by_id":1305,"modified":"2025-01-06T01:32:35.326330"},{"url":"news.yahoo.com","hosted_by":null,"green":false,"hosted_by_id":null,"modified":"2025-01-06T01:32:35.493063"},{"url":"indiatimes.com","hosted_by":null,"green":false,"hosted_by_id":null,"modified":"2025-01-06T01:32:35.682491"},{"url":"ovhcloud.com","hosted_by":"OVHcloud","green":true,"hosted_by_id":1305,"modified":"2025-01-06T01:32:36.177563"},{"url":"scribd.com","hosted_by":null,"green":false,"hosted_by_id":null,"modified":"2025-01-06T01:32:36.356025"},{"url":"dropcatch.com","hosted_by":"Cloudflare","green":true,"hosted_by_id":779,"modified":"2025-01-06T01:32:36.473404"},{"url":"bit.ly","hosted_by":null,"green":false,"hosted_by_id":null,"modified":"2025-01-06T01:32:36.908264"},{"url":"www.gov.uk","hosted_by":null,"green":false,"hosted_by_id":null,"modified":"2025-01-06T01:32:37.011014"},{"url":"de.wikipedia.org","hosted_by":null,"green":false,"hosted_by_id":null,"modified":"2025-01-06T01:32:37.165499"},{"url":"dailymail.co.uk","hosted_by":null,"green":false,"hosted_by_id":null,"modified":"2025-01-06T01:32:38.173607"},{"url":"huawei.com","hosted_by":null,"green":false,"hosted_by_id":null,"modified":"2025-01-06T01:32:39.129034"},{"url":"bbc.com","hosted_by":null,"green":false,"hosted_by_id":null,"modified":"2025-01-06T01:32:39.304821"},{"url":"wiley.com","hosted_by":null,"green":false,"hosted_by_id":null,"modified":"2025-01-06T01:32:40.270137"},{"url":"reuters.com","hosted_by":null,"green":false,"hosted_by_id":null,"modified":"2025-01-06T01:32:40.908880"},{"url":"booking.com","hosted_by":null,"green":false,"hosted_by_id":null,"modified":"2025-01-06T01:32:40.971718"},{"url":"t.co","hosted_by":"Cloudflare","green":true,"hosted_by_id":779,"modified":"2025-01-06T01:32:41.040235"},{"url":"get.google.com","hosted_by":"Google Inc.","green":true,"hosted_by_id":595,"modified":"2025-01-06T01:32:41.139551"},{"url":"fb.com","hosted_by":"Facebook","green":true,"hosted_by_id":475,"modified":"2025-01-06T01:32:41.210451"},{"url":"bloomberg.com","hosted_by":null,"green":false,"hosted_by_id":null,"modified":"2025-01-06T01:32:41.610486"},{"url":"un.org","hosted_by":null,"green":false,"hosted_by_id":null,"modified":"2025-01-06T01:32:36.221637"},{"url":"www.gov.br","hosted_by":null,"green":false,"hosted_by_id":null,"modified":"2025-01-06T01:32:36.801460"},{"url":"independent.co.uk","hosted_by":null,"green":false,"hosted_by_id":null,"modified":"2025-01-06T01:32:37.116192"},{"url":"spotify.com","hosted_by":null,"green":false,"hosted_by_id":null,"modified":"2025-01-06T01:32:37.418648"},{"url":"nasa.gov","hosted_by":null,"green":false,"hosted_by_id":null,"modified":"2025-01-06T01:32:37.700020"},{"url":"aboutads.info","hosted_by":null,"green":false,"hosted_by_id":null,"modified":"2025-01-06T01:32:37.781517"},{"url":"picasaweb.google.com","hosted_by":"Google Inc.","green":true,"hosted_by_id":595,"modified":"2025-01-06T01:32:37.826318"},{"url":"amazon.de","hosted_by":"Amazon Web Services","green":true,"hosted_by_id":697,"modified":"2025-01-06T01:32:37.892357"},{"url":"time.com","hosted_by":null,"green":false,"hosted_by_id":null,"modified":"2025-01-06T01:32:37.955004"},{"url":"huffpost.com","hosted_by":null,"green":false,"hosted_by_id":null,"modified":"2025-01-06T01:32:38.284819"},{"url":"correios.com.br","hosted_by":null,"green":false,"hosted_by_id":null,"modified":"2025-01-06T01:32:39.318337"},{"url":"telegraph.co.uk","hosted_by":null,"green":false,"hosted_by_id":null,"modified":"2025-01-06T01:32:39.630206"},{"url":"photos.google.com","hosted_by":"Google Inc.","green":true,"hosted_by_id":595,"modified":"2025-01-06T01:32:39.669231"},{"url":"aliexpress.com","hosted_by":null,"green":false,"hosted_by_id":null,"modified":"2025-01-06T01:32:39.990562"},{"url":"google.fr","hosted_by":"Google Inc.","green":true,"hosted_by_id":595,"modified":"2025-01-06T01:32:40.035034"},{"url":"washingtonpost.com","hosted_by":null,"green":false,"hosted_by_id":null,"modified":"2025-01-06T01:32:40.312085"},{"url":"usatoday.com","hosted_by":null,"green":false,"hosted_by_id":null,"modified":"2025-01-06T01:32:40.650845"},{"url":"pinterest.com","hosted_by":null,"green":false,"hosted_by_id":null,"modified":"2025-01-06T01:32:40.713883"},{"url":"youronlinechoices.com","hosted_by":"Microsoft Azure","green":true,"hosted_by_id":1091,"modified":"2025-01-06T01:32:40.775110"},{"url":"nginx.org","hosted_by":"Amazon Web Services","green":true,"hosted_by_id":697,"modified":"2025-01-06T01:32:40.794107"},{"url":"list-manage.com","hosted_by":null,"green":false,"hosted_by_id":null,"modified":"2025-01-06T01:32:37.221273"},{"url":"afternic.com","hosted_by":null,"green":false,"hosted_by_id":null,"modified":"2025-01-06T01:32:37.590988"},{"url":"planalto.gov.br","hosted_by":null,"green":false,"hosted_by_id":null,"modified":"2025-01-06T01:32:38.155578"},{"url":"terra.com.br","hosted_by":null,"green":false,"hosted_by_id":null,"modified":"2025-01-06T01:32:39.180064"},{"url":"elpais.com","hosted_by":null,"green":false,"hosted_by_id":null,"modified":"2025-01-06T01:32:39.450726"},{"url":"hatena.ne.jp","hosted_by":null,"green":false,"hosted_by_id":null,"modified":"2025-01-06T01:32:39.765605"},{"url":"mail.google.com","hosted_by":"Google Inc.","green":true,"hosted_by_id":595,"modified":"2025-01-06T01:32:39.803544"},{"url":"www.wix.com","hosted_by":"Google Inc.","green":true,"hosted_by_id":595,"modified":"2025-01-06T01:32:39.893104"},{"url":"networkadvertising.org","hosted_by":null,"green":false,"hosted_by_id":null,"modified":"2025-01-06T01:32:40.162457"},{"url":"jimdofree.com","hosted_by":null,"green":false,"hosted_by_id":null,"modified":"2025-01-06T01:32:40.176889"},{"url":"live.com","hosted_by":"Microsoft Azure","green":true,"hosted_by_id":1091,"modified":"2025-01-06T01:32:40.244232"},{"url":"cdc.gov","hosted_by":null,"green":false,"hosted_by_id":null,"modified":"2025-01-06T01:32:40.838152"},{"url":"thesun.co.uk","hosted_by":null,"green":false,"hosted_by_id":null,"modified":"2025-01-06T01:32:40.894947"},{"url":"google.co.jp","hosted_by":"Google Inc.","green":true,"hosted_by_id":595,"modified":"2025-01-06T01:32:40.935129"},{"url":"amazon.co.jp","hosted_by":"Amazon Web Services","green":true,"hosted_by_id":697,"modified":"2025-01-06T01:32:40.996144"},{"url":"tinyurl.com","hosted_by":"Cloudflare","green":true,"hosted_by_id":779,"modified":"2025-01-06T01:32:41.017104"},{"url":"wp.com","hosted_by":null,"green":false,"hosted_by_id":null,"modified":"2025-01-06T01:32:41.089108"},{"url":"hugedomains.com","hosted_by":"Cloudflare","green":true,"hosted_by_id":779,"modified":"2025-01-06T01:32:41.120499"},{"url":"archive.org","hosted_by":null,"green":false,"hosted_by_id":null,"modified":"2025-01-06T01:32:41.184406"},{"url":"huffingtonpost.com","hosted_by":null,"green":false,"hosted_by_id":null,"modified":"2025-01-06T01:32:41.248585"},{"url":"nature.com","hosted_by":null,"green":false,"hosted_by_id":null,"modified":"2025-01-06T01:32:37.946727"},{"url":"cnet.com","hosted_by":"Google Inc.","green":true,"hosted_by_id":595,"modified":"2025-01-06T01:32:38.044243"},{"url":"godaddy.com","hosted_by":null,"green":false,"hosted_by_id":null,"modified":"2025-01-06T01:32:38.360605"},{"url":"linktr.ee","hosted_by":null,"green":false,"hosted_by_id":null,"modified":"2025-01-06T01:32:38.437691"},{"url":"myaccount.google.com","hosted_by":"Google Inc.","green":true,"hosted_by_id":595,"modified":"2025-01-06T01:32:38.728096"},{"url":"foxnews.com","hosted_by":null,"green":false,"hosted_by_id":null,"modified":"2025-01-06T01:32:39.051001"},{"url":"google.co.uk","hosted_by":"Google Inc.","green":true,"hosted_by_id":595,"modified":"2025-01-06T01:32:39.084095"},{"url":"marketingplatform.google.com","hosted_by":"Google Inc.","green":true,"hosted_by_id":595,"modified":"2025-01-06T01:32:39.126528"},{"url":"reg.ru","hosted_by":null,"green":false,"hosted_by_id":null,"modified":"2025-01-06T01:32:39.547207"},{"url":"fandom.com","hosted_by":null,"green":false,"hosted_by_id":null,"modified":"2025-01-06T01:32:39.874391"},{"url":"office.com","hosted_by":"Microsoft Azure","green":true,"hosted_by_id":1091,"modified":"2025-01-06T01:32:39.895513"},{"url":"google.it","hosted_by":"Google Inc.","green":true,"hosted_by_id":595,"modified":"2025-01-06T01:32:39.927118"},{"url":"estadao.com.br","hosted_by":null,"green":false,"hosted_by_id":null,"modified":"2025-01-06T01:32:40.048001"},{"url":"mirror.co.uk","hosted_by":"Amazon Web Services","green":true,"hosted_by_id":697,"modified":"2025-01-06T01:32:40.103011"},{"url":"researchgate.net","hosted_by":"Cloudflare","green":true,"hosted_by_id":779,"modified":"2025-01-06T01:32:40.133449"},{"url":"mediafire.com","hosted_by":"Cloudflare","green":true,"hosted_by_id":779,"modified":"2025-01-06T01:32:40.193249"},{"url":"msn.com","hosted_by":"Microsoft Azure","green":true,"hosted_by_id":1091,"modified":"2025-01-06T01:32:40.272262"},{"url":"telegram.me","hosted_by":null,"green":false,"hosted_by_id":null,"modified":"2025-01-06T01:32:40.346617"},{"url":"amazon.co.uk","hosted_by":"Amazon Web Services","green":true,"hosted_by_id":697,"modified":"2025-01-06T01:32:40.408411"},{"url":"instagram.com","hosted_by":"Facebook","green":true,"hosted_by_id":475,"modified":"2025-01-06T01:32:40.442492"},{"url":"ru.wikipedia.org","hosted_by":null,"green":false,"hosted_by_id":null,"modified":"2025-01-06T01:32:41.359246"},{"url":"ytimg.com","hosted_by":null,"green":false,"hosted_by_id":null,"modified":"2025-01-06T01:32:41.481998"},{"url":"plesk.com","hosted_by":"Cloudflare","green":true,"hosted_by_id":779,"modified":"2025-01-06T01:32:41.595186"},{"url":"discord.com","hosted_by":"Cloudflare","green":true,"hosted_by_id":779,"modified":"2025-01-06T01:32:41.693808"},{"url":"forbes.com","hosted_by":null,"green":false,"hosted_by_id":null,"modified":"2025-01-06T01:32:42.244712"},{"url":"creativecommons.org","hosted_by":"Cloudflare","green":true,"hosted_by_id":779,"modified":"2025-01-06T01:32:42.344377"},{"url":"pixabay.com","hosted_by":"Cloudflare","green":true,"hosted_by_id":779,"modified":"2025-01-06T01:32:42.416657"},{"url":"4shared.com","hosted_by":null,"green":false,"hosted_by_id":null,"modified":"2025-01-06T01:32:43.018261"},{"url":"rakuten.co.jp","hosted_by":null,"green":false,"hosted_by_id":null,"modified":"2025-01-06T01:32:44.049751"},{"url":"businessinsider.com","hosted_by":null,"green":false,"hosted_by_id":null,"modified":"2025-01-06T01:32:44.155480"},{"url":"www.wikipedia.org","hosted_by":null,"green":false,"hosted_by_id":null,"modified":"2025-01-06T01:32:44.201416"},{"url":"slideshare.net","hosted_by":null,"green":false,"hosted_by_id":null,"modified":"2025-01-06T01:32:44.331827"},{"url":"webmd.com","hosted_by":null,"green":false,"hosted_by_id":null,"modified":"2025-01-06T01:32:44.710930"},{"url":"issuu.com","hosted_by":null,"green":false,"hosted_by_id":null,"modified":"2025-01-06T01:32:44.863354"},{"url":"adssettings.google.com","hosted_by":"Google Inc.","green":true,"hosted_by_id":595,"modified":"2025-01-06T01:32:44.940509"},{"url":"storage.googleapis.com","hosted_by":"Google Inc.","green":true,"hosted_by_id":595,"modified":"2025-01-06T01:32:45.014611"},{"url":"ig.com.br","hosted_by":"Amazon Web Services","green":true,"hosted_by_id":697,"modified":"2025-01-06T01:32:45.135803"},{"url":"buydomains.com","hosted_by":"Cloudflare","green":true,"hosted_by_id":779,"modified":"2025-01-06T01:32:45.309794"},{"url":"twitter.com","hosted_by":null,"green":false,"hosted_by_id":null,"modified":"2025-01-06T01:32:45.422490"},{"url":"enable-javascript.com","hosted_by":"Google Inc.","green":true,"hosted_by_id":595,"modified":"2025-01-06T01:32:45.595691"},{"url":"safety.google","hosted_by":"Google Inc.","green":true,"hosted_by_id":595,"modified":"2025-01-06T01:32:39.718298"},{"url":"tmz.com","hosted_by":null,"green":false,"hosted_by_id":null,"modified":"2025-01-06T01:32:40.042993"},{"url":"www.livejournal.com","hosted_by":null,"green":false,"hosted_by_id":null,"modified":"2025-01-06T01:32:40.132822"},{"url":"calendar.google.com","hosted_by":"Google Inc.","green":true,"hosted_by_id":595,"modified":"2025-01-06T01:32:40.178707"},{"url":"lemonde.fr","hosted_by":null,"green":false,"hosted_by_id":null,"modified":"2025-01-06T01:32:40.474928"},{"url":"change.org","hosted_by":"Cloudflare","green":true,"hosted_by_id":779,"modified":"2025-01-06T01:32:40.540345"},{"url":"privacyshield.gov","hosted_by":"Amazon Web Services","green":true,"hosted_by_id":697,"modified":"2025-01-06T01:32:40.619177"},{"url":"go.co","hosted_by":"Amazon Web Services","green":true,"hosted_by_id":697,"modified":"2025-01-06T01:32:40.773967"},{"url":"goodreads.com","hosted_by":"Amazon Web Services","green":true,"hosted_by_id":697,"modified":"2025-01-06T01:32:40.850664"},{"url":"ggpht.com","hosted_by":null,"green":false,"hosted_by_id":null,"modified":"2025-01-06T01:32:40.867516"},{"url":"oup.com","hosted_by":null,"green":false,"hosted_by_id":null,"modified":"2025-01-06T01:32:41.171518"},{"url":"guardian.co.uk","hosted_by":null,"green":false,"hosted_by_id":null,"modified":"2025-01-06T01:32:41.482473"},{"url":"amazon.es","hosted_by":"Amazon Web Services","green":true,"hosted_by_id":697,"modified":"2025-01-06T01:32:41.561333"},{"url":"google.ca","hosted_by":"Google Inc.","green":true,"hosted_by_id":595,"modified":"2025-01-06T01:32:41.608770"},{"url":"imageshack.us","hosted_by":null,"green":false,"hosted_by_id":null,"modified":"2025-01-06T01:32:42.179867"},{"url":"francetvinfo.fr","hosted_by":null,"green":false,"hosted_by_id":null,"modified":"2025-01-06T01:32:42.721521"},{"url":"ipv4.google.com","hosted_by":"Google Inc.","green":true,"hosted_by_id":595,"modified":"2025-01-06T01:32:42.811048"},{"url":"leparisien.fr","hosted_by":null,"green":false,"hosted_by_id":null,"modified":"2025-01-06T01:32:43.168027"},{"url":"books.google.com","hosted_by":"Google Inc.","green":true,"hosted_by_id":595,"modified":"2025-01-06T01:32:43.212354"},{"url":"thenai.org","hosted_by":"Xanthos","green":true,"hosted_by_id":1368,"modified":"2025-01-06T01:32:43.220338"},{"url":"theatlantic.com","hosted_by":null,"green":false,"hosted_by_id":null,"modified":"2025-01-06T01:32:45.980647"},{"url":"gnu.org","hosted_by":null,"green":false,"hosted_by_id":null,"modified":"2025-01-06T01:32:46.302812"},{"url":"surveymonkey.com","hosted_by":null,"green":false,"hosted_by_id":null,"modified":"2025-01-06T01:32:46.437385"},{"url":"hindustantimes.com","hosted_by":null,"green":false,"hosted_by_id":null,"modified":"2025-01-06T01:32:46.876656"},{"url":"cbsnews.com","hosted_by":null,"green":false,"hosted_by_id":null,"modified":"2025-01-06T01:32:47.489878"},{"url":"nintendo.com","hosted_by":"Amazon Web Services","green":true,"hosted_by_id":697,"modified":"2025-01-06T01:32:47.554137"},{"url":"it.wikipedia.org","hosted_by":null,"green":false,"hosted_by_id":null,"modified":"2025-01-06T01:32:47.856963"},{"url":"themeforest.net","hosted_by":"Cloudflare","green":true,"hosted_by_id":779,"modified":"2025-01-06T01:32:47.999890"},{"url":"addthis.com","hosted_by":null,"green":false,"hosted_by_id":null,"modified":"2025-01-06T01:32:48.382183"},{"url":"hp.com","hosted_by":null,"green":false,"hosted_by_id":null,"modified":"2025-01-06T01:32:49.301150"},{"url":"ca.gov","hosted_by":"Microsoft Azure","green":true,"hosted_by_id":1091,"modified":"2025-01-06T01:32:49.399025"},{"url":"akamaihd.net","hosted_by":null,"green":false,"hosted_by_id":null,"modified":"2025-01-06T01:32:49.489571"},{"url":"secureserver.net","hosted_by":null,"green":false,"hosted_by_id":null,"modified":"2025-01-06T01:32:49.847008"},{"url":"photos1.blogger.com","hosted_by":"Google Inc.","green":true,"hosted_by_id":595,"modified":"2025-01-06T01:32:50.136218"},{"url":"abcnews.go.com","hosted_by":null,"green":false,"hosted_by_id":null,"modified":"2025-01-06T01:32:50.382369"},{"url":"mystrikingly.com","hosted_by":null,"green":false,"hosted_by_id":null,"modified":"2025-01-06T01:32:50.683993"},{"url":"yandex.ru","hosted_by":null,"green":false,"hosted_by_id":null,"modified":"2025-01-06T01:32:50.731545"},{"url":"fb.me","hosted_by":"Facebook","green":true,"hosted_by_id":475,"modified":"2025-01-06T01:32:50.829973"},{"url":"sfgate.com","hosted_by":null,"green":false,"hosted_by_id":null,"modified":"2025-01-06T01:32:51.439397"},{"url":"parallels.com","hosted_by":null,"green":false,"hosted_by_id":null,"modified":"2025-01-06T01:32:51.858702"},{"url":"academia.edu","hosted_by":null,"green":false,"hosted_by_id":null,"modified":"2025-01-06T01:32:41.711974"},{"url":"home.pl","hosted_by":null,"green":false,"hosted_by_id":null,"modified":"2025-01-06T01:32:42.335573"},{"url":"dw.com","hosted_by":null,"green":false,"hosted_by_id":null,"modified":"2025-01-06T01:32:42.905065"},{"url":"smh.com.au","hosted_by":null,"green":false,"hosted_by_id":null,"modified":"2025-01-06T01:32:43.218407"},{"url":"news.com.au","hosted_by":null,"green":false,"hosted_by_id":null,"modified":"2025-01-06T01:32:43.488662"},{"url":"yelp.com","hosted_by":null,"green":false,"hosted_by_id":null,"modified":"2025-01-06T01:32:43.791801"},{"url":"photobucket.com","hosted_by":null,"green":false,"hosted_by_id":null,"modified":"2025-01-06T01:32:44.117014"},{"url":"amazon.fr","hosted_by":"Amazon Web Services","green":true,"hosted_by_id":697,"modified":"2025-01-06T01:32:44.195090"},{"url":"people.com","hosted_by":null,"green":false,"hosted_by_id":null,"modified":"2025-01-06T01:32:44.218338"},{"url":"example.com","hosted_by":null,"green":false,"hosted_by_id":null,"modified":"2025-01-06T01:32:44.498058"},{"url":"search.yahoo.com","hosted_by":null,"green":false,"hosted_by_id":null,"modified":"2025-01-06T01:32:45.025152"},{"url":"pexels.com","hosted_by":"Cloudflare","green":true,"hosted_by_id":779,"modified":"2025-01-06T01:32:45.048488"},{"url":"addtoany.com","hosted_by":"Cloudflare","green":true,"hosted_by_id":779,"modified":"2025-01-06T01:32:45.078556"},{"url":"samsung.com","hosted_by":null,"green":false,"hosted_by_id":null,"modified":"2025-01-06T01:32:45.391739"},{"url":"amzn.to","hosted_by":null,"green":false,"hosted_by_id":null,"modified":"2025-01-06T01:32:45.716868"},{"url":"zoom.us","hosted_by":null,"green":false,"hosted_by_id":null,"modified":"2025-01-06T01:32:46.023232"},{"url":"discord.gg","hosted_by":"Cloudflare","green":true,"hosted_by_id":779,"modified":"2025-01-06T01:32:46.087820"},{"url":"code.google.com","hosted_by":"Google Inc.","green":true,"hosted_by_id":595,"modified":"2025-01-06T01:32:46.296519"},{"url":"offset.com","hosted_by":null,"green":false,"hosted_by_id":null,"modified":"2025-01-06T01:32:46.634046"},{"url":"theconversation.com","hosted_by":null,"green":false,"hosted_by_id":null,"modified":"2025-01-06T01:32:46.703027"},{"url":"ebay.com","hosted_by":null,"green":false,"hosted_by_id":null,"modified":"2025-01-06T01:32:42.960923"},{"url":"telegra.ph","hosted_by":null,"green":false,"hosted_by_id":null,"modified":"2025-01-06T01:32:43.283923"},{"url":"pl.wikipedia.org","hosted_by":null,"green":false,"hosted_by_id":null,"modified":"2025-01-06T01:32:43.340927"},{"url":"ibm.com","hosted_by":null,"green":false,"hosted_by_id":null,"modified":"2025-01-06T01:32:43.655530"},{"url":"techcrunch.com","hosted_by":null,"green":false,"hosted_by_id":null,"modified":"2025-01-06T01:32:44.171962"},{"url":"arxiv.org","hosted_by":null,"green":false,"hosted_by_id":null,"modified":"2025-01-06T01:32:44.494080"},{"url":"nhk.or.jp","hosted_by":null,"green":false,"hosted_by_id":null,"modified":"2025-01-06T01:32:44.511754"},{"url":"airbnb.com","hosted_by":"Amazon Web Services","green":true,"hosted_by_id":697,"modified":"2025-01-06T01:32:44.579758"},{"url":"aol.com","hosted_by":null,"green":false,"hosted_by_id":null,"modified":"2025-01-06T01:32:44.902598"},{"url":"namebright.com","hosted_by":"Cloudflare","green":true,"hosted_by_id":779,"modified":"2025-01-06T01:32:44.930684"},{"url":"engadget.com","hosted_by":null,"green":false,"hosted_by_id":null,"modified":"2025-01-06T01:32:44.992636"},{"url":"namecheap.com","hosted_by":null,"green":false,"hosted_by_id":null,"modified":"2025-01-06T01:32:45.304313"},{"url":"disqus.com","hosted_by":null,"green":false,"hosted_by_id":null,"modified":"2025-01-06T01:32:45.628392"},{"url":"unesco.org","hosted_by":null,"green":false,"hosted_by_id":null,"modified":"2025-01-06T01:32:46.202283"},{"url":"sciencedirect.com","hosted_by":"Cloudflare","green":true,"hosted_by_id":779,"modified":"2025-01-06T01:32:46.261020"},{"url":"id.wikipedia.org","hosted_by":null,"green":false,"hosted_by_id":null,"modified":"2025-01-06T01:32:46.315567"},{"url":"newyorker.com","hosted_by":null,"green":false,"hosted_by_id":null,"modified":"2025-01-06T01:32:46.636957"},{"url":"qq.com","hosted_by":null,"green":false,"hosted_by_id":null,"modified":"2025-01-06T01:32:47.195878"},{"url":"ikea.com","hosted_by":null,"green":false,"hosted_by_id":null,"modified":"2025-01-06T01:32:47.469022"},{"url":"domainmarket.com","hosted_by":"Cloudflare","green":true,"hosted_by_id":779,"modified":"2025-01-06T01:32:47.489216"},{"url":"taringa.net","hosted_by":null,"green":false,"hosted_by_id":null,"modified":"2025-01-06T01:32:44.045378"},{"url":"unsplash.com","hosted_by":null,"green":false,"hosted_by_id":null,"modified":"2025-01-06T01:32:44.354246"},{"url":"rapidshare.com","hosted_by":null,"green":false,"hosted_by_id":null,"modified":"2025-01-06T01:32:44.366016"},{"url":"ea.com","hosted_by":null,"green":false,"hosted_by_id":null,"modified":"2025-01-06T01:32:44.643345"},{"url":"skype.com","hosted_by":"Microsoft Azure","green":true,"hosted_by_id":1091,"modified":"2025-01-06T01:32:44.703338"},{"url":"wikia.com","hosted_by":null,"green":false,"hosted_by_id":null,"modified":"2025-01-06T01:32:44.970656"},{"url":"newsweek.com","hosted_by":null,"green":false,"hosted_by_id":null,"modified":"2025-01-06T01:32:45.286126"},{"url":"mit.edu","hosted_by":null,"green":false,"hosted_by_id":null,"modified":"2025-01-06T01:32:45.582283"},{"url":"cambridge.org","hosted_by":"Cloudflare","green":true,"hosted_by_id":779,"modified":"2025-01-06T01:32:45.636758"},{"url":"wired.com","hosted_by":null,"green":false,"hosted_by_id":null,"modified":"2025-01-06T01:32:45.943311"},{"url":"economist.com","hosted_by":"Cloudflare","green":true,"hosted_by_id":779,"modified":"2025-01-06T01:32:46.009143"},{"url":"buzzfeed.com","hosted_by":null,"green":false,"hosted_by_id":null,"modified":"2025-01-06T01:32:46.086326"},{"url":"detik.com","hosted_by":null,"green":false,"hosted_by_id":null,"modified":"2025-01-06T01:32:47.073039"},{"url":"britannica.com","hosted_by":"Amazon Web Services","green":true,"hosted_by_id":697,"modified":"2025-01-06T01:32:47.143249"},{"url":"yahoo.co.jp","hosted_by":null,"green":false,"hosted_by_id":null,"modified":"2025-01-06T01:32:47.696040"},{"url":"springer.com","hosted_by":null,"green":false,"hosted_by_id":null,"modified":"2025-01-06T01:32:48.004354"},{"url":"quora.com","hosted_by":"Amazon Web Services","green":true,"hosted_by_id":697,"modified":"2025-01-06T01:32:48.085223"},{"url":"nydailynews.com","hosted_by":null,"green":false,"hosted_by_id":null,"modified":"2025-01-06T01:32:48.384547"},{"url":"doi.org","hosted_by":"Cloudflare","green":true,"hosted_by_id":779,"modified":"2025-01-06T01:32:48.410941"},{"url":"nikkei.com","hosted_by":null,"green":false,"hosted_by_id":null,"modified":"2025-01-06T01:32:48.735025"},{"url":"picasa.google.com","hosted_by":"Google Inc.","green":true,"hosted_by_id":595,"modified":"2025-01-06T01:32:44.732690"},{"url":"gizmodo.com","hosted_by":"Cloudflare","green":true,"hosted_by_id":779,"modified":"2025-01-06T01:32:44.820750"},{"url":"amazonaws.com","hosted_by":"Amazon Web Services","green":true,"hosted_by_id":697,"modified":"2025-01-06T01:32:44.915874"},{"url":"wsj.com","hosted_by":null,"green":false,"hosted_by_id":null,"modified":"2025-01-06T01:32:45.309984"},{"url":"weibo.com","hosted_by":null,"green":false,"hosted_by_id":null,"modified":"2025-01-06T01:32:45.751798"},{"url":"latimes.com","hosted_by":null,"green":false,"hosted_by_id":null,"modified":"2025-01-06T01:32:46.095674"},{"url":"workspace.google.com","hosted_by":"Google Inc.","green":true,"hosted_by_id":595,"modified":"2025-01-06T01:32:46.176383"},{"url":"t-online.de","hosted_by":"Amazon Web Services","green":true,"hosted_by_id":697,"modified":"2025-01-06T01:32:46.325837"},{"url":"trustpilot.com","hosted_by":"Amazon Web Services","green":true,"hosted_by_id":697,"modified":"2025-01-06T01:32:46.441230"},{"url":"steampowered.com","hosted_by":null,"green":false,"hosted_by_id":null,"modified":"2025-01-06T01:32:47.015624"},{"url":"vkontakte.ru","hosted_by":null,"green":false,"hosted_by_id":null,"modified":"2025-01-06T01:32:47.441963"},{"url":"dailystar.co.uk","hosted_by":"Amazon Web Services","green":true,"hosted_by_id":697,"modified":"2025-01-06T01:32:47.540801"},{"url":"psychologytoday.com","hosted_by":"Amazon Web Services","green":true,"hosted_by_id":697,"modified":"2025-01-06T01:32:47.630646"},{"url":"yandex.com","hosted_by":null,"green":false,"hosted_by_id":null,"modified":"2025-01-06T01:32:48.506117"},{"url":"sedoparking.com","hosted_by":null,"green":false,"hosted_by_id":null,"modified":"2025-01-06T01:32:48.703794"},{"url":"instructables.com","hosted_by":null,"green":false,"hosted_by_id":null,"modified":"2025-01-06T01:32:49.112542"},{"url":"ouest-france.fr","hosted_by":null,"green":false,"hosted_by_id":null,"modified":"2025-01-06T01:32:49.508442"},{"url":"nypost.com","hosted_by":null,"green":false,"hosted_by_id":null,"modified":"2025-01-06T01:32:49.607000"},{"url":"loc.gov","hosted_by":"Cloudflare","green":true,"hosted_by_id":779,"modified":"2025-01-06T01:32:49.703199"},{"url":"ja.wikipedia.org","hosted_by":null,"green":false,"hosted_by_id":null,"modified":"2025-01-06T01:32:49.756265"},{"url":"rtve.es","hosted_by":null,"green":false,"hosted_by_id":null,"modified":"2025-01-06T01:32:46.188596"},{"url":"nationalgeographic.com","hosted_by":null,"green":false,"hosted_by_id":null,"modified":"2025-01-06T01:32:46.461788"},{"url":"express.co.uk","hosted_by":null,"green":false,"hosted_by_id":null,"modified":"2025-01-06T01:32:46.802623"},{"url":"yadi.sk","hosted_by":null,"green":false,"hosted_by_id":null,"modified":"2025-01-06T01:32:47.086210"},{"url":"groups.google.com","hosted_by":"Google Inc.","green":true,"hosted_by_id":595,"modified":"2025-01-06T01:32:47.405071"},{"url":"thetimes.co.uk","hosted_by":"Amazon Web Services","green":true,"hosted_by_id":697,"modified":"2025-01-06T01:32:47.476196"},{"url":"sputniknews.com","hosted_by":null,"green":false,"hosted_by_id":null,"modified":"2025-01-06T01:32:48.058646"},{"url":"mozilla.com","hosted_by":"Google Inc.","green":true,"hosted_by_id":595,"modified":"2025-01-06T01:32:48.125173"},{"url":"www.over-blog.com","hosted_by":null,"green":false,"hosted_by_id":null,"modified":"2025-01-06T01:32:48.832729"},{"url":"naver.com","hosted_by":null,"green":false,"hosted_by_id":null,"modified":"2025-01-06T01:32:49.129370"},{"url":"gmail.com","hosted_by":"Google Inc.","green":true,"hosted_by_id":595,"modified":"2025-01-06T01:32:49.170655"},{"url":"tripadvisor.com","hosted_by":null,"green":false,"hosted_by_id":null,"modified":"2025-01-06T01:32:49.493880"},{"url":"oracle.com","hosted_by":null,"green":false,"hosted_by_id":null,"modified":"2025-01-06T01:32:49.578962"},{"url":"hubspot.com","hosted_by":"Cloudflare","green":true,"hosted_by_id":779,"modified":"2025-01-06T01:32:49.602276"},{"url":"insider.com","hosted_by":null,"green":false,"hosted_by_id":null,"modified":"2025-01-06T01:32:49.674781"},{"url":"ndtv.com","hosted_by":null,"green":false,"hosted_by_id":null,"modified":"2025-01-06T01:32:49.957493"},{"url":"mynavi.jp","hosted_by":null,"green":false,"hosted_by_id":null,"modified":"2025-01-06T01:32:50.371710"},{"url":"php.net","hosted_by":null,"green":false,"hosted_by_id":null,"modified":"2025-01-06T01:32:50.632335"},{"url":"rt.com","hosted_by":null,"green":false,"hosted_by_id":null,"modified":"2025-01-06T01:32:51.180182"},{"url":"bing.com","hosted_by":"Microsoft Azure","green":true,"hosted_by_id":1091,"modified":"2025-01-06T01:32:51.214637"},{"url":"timeweb.ru","hosted_by":null,"green":false,"hosted_by_id":null,"modified":"2025-01-06T01:32:46.918549"},{"url":"clarin.com","hosted_by":"Cloudflare","green":true,"hosted_by_id":779,"modified":"2025-01-06T01:32:46.953819"},{"url":"google.ru","hosted_by":"Google Inc.","green":true,"hosted_by_id":595,"modified":"2025-01-06T01:32:47.007354"},{"url":"standard.co.uk","hosted_by":"Cloudflare","green":true,"hosted_by_id":779,"modified":"2025-01-06T01:32:47.040471"},{"url":"sciencedaily.com","hosted_by":null,"green":false,"hosted_by_id":null,"modified":"2025-01-06T01:32:47.358548"},{"url":"doubleclick.net","hosted_by":"Google Inc.","green":true,"hosted_by_id":595,"modified":"2025-01-06T01:32:47.403324"},{"url":"perfectdomain.com","hosted_by":"Cloudflare","green":true,"hosted_by_id":779,"modified":"2025-01-06T01:32:47.438764"},{"url":"cnbc.com","hosted_by":"Amazon Web Services","green":true,"hosted_by_id":697,"modified":"2025-01-06T01:32:47.525225"},{"url":"statista.com","hosted_by":null,"green":false,"hosted_by_id":null,"modified":"2025-01-06T01:32:47.591131"},{"url":"bloglovin.com","hosted_by":"Cloudflare","green":true,"hosted_by_id":779,"modified":"2025-01-06T01:32:47.622016"},{"url":"excite.co.jp","hosted_by":null,"green":false,"hosted_by_id":null,"modified":"2025-01-06T01:32:48.086178"},{"url":"netflix.com","hosted_by":"Amazon Web Services","green":true,"hosted_by_id":697,"modified":"2025-01-06T01:32:48.109101"},{"url":"hollywoodreporter.com","hosted_by":null,"green":false,"hosted_by_id":null,"modified":"2025-01-06T01:32:48.413246"},{"url":"mashable.com","hosted_by":"Cloudflare","green":true,"hosted_by_id":779,"modified":"2025-01-06T01:32:48.445365"},{"url":"espn.com","hosted_by":null,"green":false,"hosted_by_id":null,"modified":"2025-01-06T01:32:48.763387"},{"url":"playstation.com","hosted_by":"Amazon Web Services","green":true,"hosted_by_id":697,"modified":"2025-01-06T01:32:48.809257"},{"url":"lavanguardia.com","hosted_by":null,"green":false,"hosted_by_id":null,"modified":"2025-01-06T01:32:49.130093"},{"url":"cornell.edu","hosted_by":null,"green":false,"hosted_by_id":null,"modified":"2025-01-06T01:32:49.702223"},{"url":"cbc.ca","hosted_by":null,"green":false,"hosted_by_id":null,"modified":"2025-01-06T01:32:50.036949"},{"url":"alicdn.com","hosted_by":null,"green":false,"hosted_by_id":null,"modified":"2025-01-06T01:32:50.614899"},{"url":"gofundme.com","hosted_by":null,"green":false,"hosted_by_id":null,"modified":"2025-01-06T01:32:47.959216"},{"url":"mega.nz","hosted_by":null,"green":false,"hosted_by_id":null,"modified":"2025-01-06T01:32:48.465181"},{"url":"clickbank.net","hosted_by":null,"green":false,"hosted_by_id":null,"modified":"2025-01-06T01:32:48.479673"},{"url":"disney.com","hosted_by":"Google Inc.","green":true,"hosted_by_id":595,"modified":"2025-01-06T01:32:48.546547"},{"url":"npr.org","hosted_by":null,"green":false,"hosted_by_id":null,"modified":"2025-01-06T01:32:48.853521"},{"url":"apache.org","hosted_by":null,"green":false,"hosted_by_id":null,"modified":"2025-01-06T01:32:48.881008"},{"url":"finance.yahoo.com","hosted_by":null,"green":false,"hosted_by_id":null,"modified":"2025-01-06T01:32:48.916158"},{"url":"zendesk.com","hosted_by":null,"green":false,"hosted_by_id":null,"modified":"2025-01-06T01:32:49.236176"},{"url":"cointernet.com.co","hosted_by":"Amazon Web Services","green":true,"hosted_by_id":697,"modified":"2025-01-06T01:32:49.476334"},{"url":"20minutos.es","hosted_by":null,"green":false,"hosted_by_id":null,"modified":"2025-01-06T01:32:49.786984"},{"url":"ted.com","hosted_by":"Amazon Web Services","green":true,"hosted_by_id":697,"modified":"2025-01-06T01:32:49.857049"},{"url":"eventbrite.com","hosted_by":null,"green":false,"hosted_by_id":null,"modified":"2025-01-06T01:32:49.915555"},{"url":"marca.com","hosted_by":null,"green":false,"hosted_by_id":null,"modified":"2025-01-06T01:32:50.466095"},{"url":"cpanel.com","hosted_by":"Cloudflare","green":true,"hosted_by_id":779,"modified":"2025-01-06T01:32:50.499801"},{"url":"m.wikipedia.org","hosted_by":null,"green":false,"hosted_by_id":null,"modified":"2025-01-06T01:32:50.882847"},{"url":"sendspace.com","hosted_by":"Cloudflare","green":true,"hosted_by_id":779,"modified":"2025-01-06T01:32:50.914705"},{"url":"kickstarter.com","hosted_by":"Cloudflare","green":true,"hosted_by_id":779,"modified":"2025-01-06T01:32:50.937784"},{"url":"icann.org","hosted_by":null,"green":false,"hosted_by_id":null,"modified":"2025-01-06T01:32:51.500283"},{"url":"translate.google.com","hosted_by":"Google Inc.","green":true,"hosted_by_id":595,"modified":"2025-01-06T01:32:51.539068"},{"url":"ft.com","hosted_by":null,"green":false,"hosted_by_id":null,"modified":"2025-01-06T01:32:51.859543"},{"url":"elmundo.es","hosted_by":null,"green":false,"hosted_by_id":null,"modified":"2025-01-06T01:32:53.184738"},{"url":"bandcamp.com","hosted_by":"Axis12 Ltd","green":true,"hosted_by_id":1186,"modified":"2025-01-06T01:32:53.301123"},{"url":"ssl-images-amazon.com","hosted_by":null,"green":false,"hosted_by_id":null,"modified":"2025-01-06T01:32:53.445627"},{"url":"outlook.com","hosted_by":null,"green":false,"hosted_by_id":null,"modified":"2025-01-06T01:32:53.997199"},{"url":"abc.es","hosted_by":null,"green":false,"hosted_by_id":null,"modified":"2025-01-06T01:32:54.159045"},{"url":"nbcnews.com","hosted_by":"Amazon Web Services","green":true,"hosted_by_id":697,"modified":"2025-01-06T01:32:54.645346"},{"url":"twitch.tv","hosted_by":null,"green":false,"hosted_by_id":null,"modified":"2025-01-06T01:32:54.845142"},{"url":"ziddu.com","hosted_by":"OVHcloud","green":true,"hosted_by_id":1305,"modified":"2025-01-06T01:32:55.386992"},{"url":"spiegel.de","hosted_by":"Link11 GmbH","green":true,"hosted_by_id":1214,"modified":"2025-01-06T01:32:55.813457"},{"url":"sedo.com","hosted_by":"Cloudflare","green":true,"hosted_by_id":779,"modified":"2025-01-06T01:32:55.908848"},{"url":"zdf.de","hosted_by":null,"green":false,"hosted_by_id":null,"modified":"2025-01-06T01:32:56.285488"},{"url":"harvard.edu","hosted_by":null,"green":false,"hosted_by_id":null,"modified":"2025-01-06T01:32:56.602604"},{"url":"zippyshare.com","hosted_by":"OVHcloud","green":true,"hosted_by_id":1305,"modified":"2025-01-06T01:32:57.050428"},{"url":"walmart.com","hosted_by":null,"green":false,"hosted_by_id":null,"modified":"2025-01-06T01:32:57.386600"},{"url":"deezer.com","hosted_by":null,"green":false,"hosted_by_id":null,"modified":"2025-01-06T01:32:57.568662"},{"url":"ign.com","hosted_by":null,"green":false,"hosted_by_id":null,"modified":"2025-01-06T01:32:57.692274"},{"url":"my.yahoo.com","hosted_by":null,"green":false,"hosted_by_id":null,"modified":"2025-01-06T01:32:58.702755"},{"url":"android.com","hosted_by":"Google Inc.","green":true,"hosted_by_id":595,"modified":"2025-01-06T01:32:58.894170"},{"url":"netlify.app","hosted_by":"Amazon Web Services","green":true,"hosted_by_id":697,"modified":"2025-01-06T01:32:58.978584"},{"url":"abc.net.au","hosted_by":null,"green":false,"hosted_by_id":null,"modified":"2025-01-06T01:32:59.148674"},{"url":"wikihow.com","hosted_by":null,"green":false,"hosted_by_id":null,"modified":"2025-01-06T01:32:49.714598"},{"url":"pbs.org","hosted_by":"Amazon Web Services","green":true,"hosted_by_id":697,"modified":"2025-01-06T01:32:49.792010"},{"url":"stanford.edu","hosted_by":null,"green":false,"hosted_by_id":null,"modified":"2025-01-06T01:32:50.068902"},{"url":"variety.com","hosted_by":null,"green":false,"hosted_by_id":null,"modified":"2025-01-06T01:32:50.382860"},{"url":"soundcloud.com","hosted_by":null,"green":false,"hosted_by_id":null,"modified":"2025-01-06T01:32:50.690133"},{"url":"lin.ee","hosted_by":null,"green":false,"hosted_by_id":null,"modified":"2025-01-06T01:32:51.245528"},{"url":"sakura.ne.jp","hosted_by":null,"green":false,"hosted_by_id":null,"modified":"2025-01-06T01:32:51.790748"},{"url":"vistaprint.com","hosted_by":"Cloudflare","green":true,"hosted_by_id":779,"modified":"2025-01-06T01:32:51.820880"},{"url":"dreamstime.com","hosted_by":null,"green":false,"hosted_by_id":null,"modified":"2025-01-06T01:32:52.135136"},{"url":"google.nl","hosted_by":"Google Inc.","green":true,"hosted_by_id":595,"modified":"2025-01-06T01:32:52.182123"},{"url":"theverge.com","hosted_by":null,"green":false,"hosted_by_id":null,"modified":"2025-01-06T01:32:52.254918"},{"url":"shutterstock.com","hosted_by":null,"green":false,"hosted_by_id":null,"modified":"2025-01-06T01:32:52.551593"},{"url":"about.com","hosted_by":null,"green":false,"hosted_by_id":null,"modified":"2025-01-06T01:32:52.575931"},{"url":"vice.com","hosted_by":null,"green":false,"hosted_by_id":null,"modified":"2025-01-06T01:32:52.889280"},{"url":"google.pl","hosted_by":"Google Inc.","green":true,"hosted_by_id":595,"modified":"2025-01-06T01:32:52.920009"},{"url":"plos.org","hosted_by":"Cloudflare","green":true,"hosted_by_id":779,"modified":"2025-01-06T01:32:52.949860"},{"url":"redbull.com","hosted_by":null,"green":false,"hosted_by_id":null,"modified":"2025-01-06T01:32:53.238860"},{"url":"lefigaro.fr","hosted_by":null,"green":false,"hosted_by_id":null,"modified":"2025-01-06T01:32:53.520600"},{"url":"sapo.pt","hosted_by":null,"green":false,"hosted_by_id":null,"modified":"2025-01-06T01:32:54.222314"},{"url":"rambler.ru","hosted_by":null,"green":false,"hosted_by_id":null,"modified":"2025-01-06T01:32:54.542762"},{"url":"howstuffworks.com","hosted_by":null,"green":false,"hosted_by_id":null,"modified":"2025-01-06T01:33:17.146077"},{"url":"blackberry.com","hosted_by":null,"green":false,"hosted_by_id":null,"modified":"2025-01-06T01:33:17.626101"},{"url":"admin.ch","hosted_by":null,"green":false,"hosted_by_id":null,"modified":"2025-01-06T01:33:18.130327"},{"url":"interia.pl","hosted_by":null,"green":false,"hosted_by_id":null,"modified":"2025-01-06T01:33:18.646256"},{"url":"thetimes.com","hosted_by":"Amazon Web Services","green":true,"hosted_by_id":697,"modified":"2025-01-06T01:33:18.807317"},{"url":"amazon.it","hosted_by":"Amazon Web Services","green":true,"hosted_by_id":697,"modified":"2025-01-06T01:33:18.960995"},{"url":"com.com","hosted_by":"Cloudflare","green":true,"hosted_by_id":779,"modified":"2025-01-06T01:33:19.046708"},{"url":"bfmtv.com","hosted_by":"Amazon Web Services","green":true,"hosted_by_id":697,"modified":"2025-01-06T01:33:19.180945"},{"url":"public-api.wordpress.com","hosted_by":null,"green":false,"hosted_by_id":null,"modified":"2025-01-06T01:33:19.272679"},{"url":"orange.fr","hosted_by":null,"green":false,"hosted_by_id":null,"modified":"2025-01-06T01:33:19.685692"},{"url":"scholastic.com","hosted_by":null,"green":false,"hosted_by_id":null,"modified":"2025-01-06T01:33:20.090369"},{"url":"sueddeutsche.de","hosted_by":null,"green":false,"hosted_by_id":null,"modified":"2025-01-06T01:33:20.605047"},{"url":"bmj.com","hosted_by":null,"green":false,"hosted_by_id":null,"modified":"2025-01-06T01:33:20.846993"},{"url":"archives.gov","hosted_by":"Amazon Web Services","green":true,"hosted_by_id":697,"modified":"2025-01-06T01:33:21.460680"},{"url":"cbslocal.com","hosted_by":null,"green":false,"hosted_by_id":null,"modified":"2025-01-06T01:33:22.111032"},{"url":"wallpapers.com","hosted_by":null,"green":false,"hosted_by_id":null,"modified":"2025-01-06T01:33:22.568078"},{"url":"mailchi.mp","hosted_by":null,"green":false,"hosted_by_id":null,"modified":"2025-01-06T01:33:22.796337"},{"url":"ads.google.com","hosted_by":"Google Inc.","green":true,"hosted_by_id":595,"modified":"2025-01-06T01:33:22.870238"},{"url":"search.google.com","hosted_by":"Google Inc.","green":true,"hosted_by_id":595,"modified":"2025-01-06T01:33:22.953380"},{"url":"sciencemag.org","hosted_by":"Amazon Web Services","green":true,"hosted_by_id":697,"modified":"2025-01-06T01:33:23.255501"},{"url":"worldbank.org","hosted_by":null,"green":false,"hosted_by_id":null,"modified":"2025-01-06T01:32:51.952064"},{"url":"intel.com","hosted_by":"Microsoft Azure","green":true,"hosted_by_id":1091,"modified":"2025-01-06T01:32:52.010030"},{"url":"gooyaabitemplates.com","hosted_by":"Cloudflare","green":true,"hosted_by_id":779,"modified":"2025-01-06T01:32:52.038341"},{"url":"chinadaily.com.cn","hosted_by":null,"green":false,"hosted_by_id":null,"modified":"2025-01-06T01:32:52.604833"},{"url":"goo.ne.jp","hosted_by":null,"green":false,"hosted_by_id":null,"modified":"2025-01-06T01:32:53.173256"},{"url":"bitly.com","hosted_by":null,"green":false,"hosted_by_id":null,"modified":"2025-01-06T01:32:53.490710"},{"url":"jstor.org","hosted_by":null,"green":false,"hosted_by_id":null,"modified":"2025-01-06T01:32:53.909470"},{"url":"usgs.gov","hosted_by":null,"green":false,"hosted_by_id":null,"modified":"2025-01-06T01:32:54.471211"},{"url":"as.com","hosted_by":null,"green":false,"hosted_by_id":null,"modified":"2025-01-06T01:32:54.742709"},{"url":"freepik.com","hosted_by":"Google Inc.","green":true,"hosted_by_id":595,"modified":"2025-01-06T01:32:54.792638"},{"url":"thehill.com","hosted_by":null,"green":false,"hosted_by_id":null,"modified":"2025-01-06T01:32:54.874599"},{"url":"trello.com","hosted_by":null,"green":false,"hosted_by_id":null,"modified":"2025-01-06T01:32:55.180323"},{"url":"depositphotos.com","hosted_by":null,"green":false,"hosted_by_id":null,"modified":"2025-01-06T01:32:55.751267"},{"url":"gsmarena.com","hosted_by":"Hetzner Online GmbH","green":true,"hosted_by_id":131,"modified":"2025-01-06T01:32:56.127899"},{"url":"messenger.com","hosted_by":"Facebook","green":true,"hosted_by_id":475,"modified":"2025-01-06T01:32:56.159702"},{"url":"amazon.ca","hosted_by":"Amazon Web Services","green":true,"hosted_by_id":697,"modified":"2025-01-06T01:32:56.223649"},{"url":"pcmag.com","hosted_by":"Cloudflare","green":true,"hosted_by_id":779,"modified":"2025-01-06T01:32:56.252850"},{"url":"medlineplus.gov","hosted_by":null,"green":false,"hosted_by_id":null,"modified":"2025-01-06T01:32:56.594387"},{"url":"marketwatch.com","hosted_by":null,"green":false,"hosted_by_id":null,"modified":"2025-01-06T01:32:56.923347"},{"url":"calendly.com","hosted_by":"Cloudflare","green":true,"hosted_by_id":779,"modified":"2025-01-06T01:32:56.952408"},{"url":"iso.org","hosted_by":null,"green":false,"hosted_by_id":null,"modified":"2025-01-06T01:32:52.992621"},{"url":"m.me","hosted_by":"Facebook","green":true,"hosted_by_id":475,"modified":"2025-01-06T01:32:53.040494"},{"url":"upenn.edu","hosted_by":null,"green":false,"hosted_by_id":null,"modified":"2025-01-06T01:32:53.068552"},{"url":"fifa.com","hosted_by":null,"green":false,"hosted_by_id":null,"modified":"2025-01-06T01:32:53.388007"},{"url":"bustle.com","hosted_by":null,"green":false,"hosted_by_id":null,"modified":"2025-01-06T01:32:53.413560"},{"url":"columbia.edu","hosted_by":"Cloudflare","green":true,"hosted_by_id":779,"modified":"2025-01-06T01:32:53.490374"},{"url":"boston.com","hosted_by":"Cloudflare","green":true,"hosted_by_id":779,"modified":"2025-01-06T01:32:53.526558"},{"url":"g.co","hosted_by":"Google Inc.","green":true,"hosted_by_id":595,"modified":"2025-01-06T01:32:53.570627"},{"url":"urbandictionary.com","hosted_by":"Google Inc.","green":true,"hosted_by_id":595,"modified":"2025-01-06T01:32:53.636851"},{"url":"gettyimages.com","hosted_by":null,"green":false,"hosted_by_id":null,"modified":"2025-01-06T01:32:53.909093"},{"url":"usnews.com","hosted_by":null,"green":false,"hosted_by_id":null,"modified":"2025-01-06T01:32:54.230499"},{"url":"123rf.com","hosted_by":null,"green":false,"hosted_by_id":null,"modified":"2025-01-06T01:32:54.521133"},{"url":"nba.com","hosted_by":null,"green":false,"hosted_by_id":null,"modified":"2025-01-06T01:32:54.609136"},{"url":"weforum.org","hosted_by":"Amazon Web Services","green":true,"hosted_by_id":697,"modified":"2025-01-06T01:32:54.682674"},{"url":"alexa.com","hosted_by":"Amazon Web Services","green":true,"hosted_by_id":697,"modified":"2025-01-06T01:32:54.753373"},{"url":"bigcommerce.com","hosted_by":null,"green":false,"hosted_by_id":null,"modified":"2025-01-06T01:32:55.313410"},{"url":"weather.com","hosted_by":null,"green":false,"hosted_by_id":null,"modified":"2025-01-06T01:32:55.595651"},{"url":"fortune.com","hosted_by":null,"green":false,"hosted_by_id":null,"modified":"2025-01-06T01:32:55.667734"},{"url":"vanityfair.com","hosted_by":null,"green":false,"hosted_by_id":null,"modified":"2025-01-06T01:32:55.993122"},{"url":"telegram.org","hosted_by":null,"green":false,"hosted_by_id":null,"modified":"2025-01-06T01:32:56.309315"},{"url":"mayoclinic.org","hosted_by":null,"green":false,"hosted_by_id":null,"modified":"2025-01-06T01:32:54.214679"},{"url":"macrumors.com","hosted_by":"Cloudflare","green":true,"hosted_by_id":779,"modified":"2025-01-06T01:32:54.236582"},{"url":"dell.com","hosted_by":null,"green":false,"hosted_by_id":null,"modified":"2025-01-06T01:32:54.791874"},{"url":"scmp.com","hosted_by":"Cloudflare","green":true,"hosted_by_id":779,"modified":"2025-01-06T01:32:54.816748"},{"url":"salesforce.com","hosted_by":null,"green":false,"hosted_by_id":null,"modified":"2025-01-06T01:32:55.379960"},{"url":"miit.gov.cn","hosted_by":null,"green":false,"hosted_by_id":null,"modified":"2025-01-06T01:32:59.299813"},{"url":"chaturbate.com","hosted_by":"Cloudflare","green":true,"hosted_by_id":779,"modified":"2025-01-06T01:32:59.329977"},{"url":"xda-developers.com","hosted_by":"Amazon Web Services","green":true,"hosted_by_id":697,"modified":"2025-01-06T01:32:59.408379"},{"url":"house.gov","hosted_by":null,"green":false,"hosted_by_id":null,"modified":"2025-01-06T01:32:59.715910"},{"url":"imgur.com","hosted_by":null,"green":false,"hosted_by_id":null,"modified":"2025-01-06T01:32:59.773071"},{"url":"lg.com","hosted_by":null,"green":false,"hosted_by_id":null,"modified":"2025-01-06T01:33:00.079452"},{"url":"merriam-webster.com","hosted_by":null,"green":false,"hosted_by_id":null,"modified":"2025-01-06T01:33:00.397804"},{"url":"lexpress.fr","hosted_by":null,"green":false,"hosted_by_id":null,"modified":"2025-01-06T01:33:00.949010"},{"url":"jhu.edu","hosted_by":null,"green":false,"hosted_by_id":null,"modified":"2025-01-06T01:33:01.505935"},{"url":"asus.com","hosted_by":null,"green":false,"hosted_by_id":null,"modified":"2025-01-06T01:33:02.060087"},{"url":"history.com","hosted_by":null,"green":false,"hosted_by_id":null,"modified":"2025-01-06T01:33:02.319761"},{"url":"xbox.com","hosted_by":"Microsoft Azure","green":true,"hosted_by_id":1091,"modified":"2025-01-06T01:33:02.386122"},{"url":"google.com.tw","hosted_by":"Google Inc.","green":true,"hosted_by_id":595,"modified":"2025-01-06T01:33:02.427099"},{"url":"usda.gov","hosted_by":null,"green":false,"hosted_by_id":null,"modified":"2025-01-06T01:33:02.995778"},{"url":"businesswire.com","hosted_by":null,"green":false,"hosted_by_id":null,"modified":"2025-01-06T01:33:03.300811"},{"url":"justgiving.com","hosted_by":null,"green":false,"hosted_by_id":null,"modified":"2025-01-06T01:32:54.958605"},{"url":"mysql.com","hosted_by":null,"green":false,"hosted_by_id":null,"modified":"2025-01-06T01:32:55.027774"},{"url":"mixcloud.com","hosted_by":"Cloudflare","green":true,"hosted_by_id":779,"modified":"2025-01-06T01:32:55.058771"},{"url":"asahi.com","hosted_by":null,"green":false,"hosted_by_id":null,"modified":"2025-01-06T01:32:55.369720"},{"url":"utexas.edu","hosted_by":null,"green":false,"hosted_by_id":null,"modified":"2025-01-06T01:32:55.402506"},{"url":"uber.com","hosted_by":null,"green":false,"hosted_by_id":null,"modified":"2025-01-06T01:32:55.726561"},{"url":"kakao.com","hosted_by":null,"green":false,"hosted_by_id":null,"modified":"2025-01-06T01:32:56.270138"},{"url":"digg.com","hosted_by":"Cloudflare","green":true,"hosted_by_id":779,"modified":"2025-01-06T01:32:56.346521"},{"url":"indiegogo.com","hosted_by":"Google Inc.","green":true,"hosted_by_id":595,"modified":"2025-01-06T01:32:56.392890"},{"url":"google.co.in","hosted_by":"Google Inc.","green":true,"hosted_by_id":595,"modified":"2025-01-06T01:32:56.426310"},{"url":"ibtimes.com","hosted_by":"Amazon Web Services","green":true,"hosted_by_id":697,"modified":"2025-01-06T01:32:56.494402"},{"url":"bp2.blogger.com","hosted_by":"Google Inc.","green":true,"hosted_by_id":595,"modified":"2025-01-06T01:32:56.665556"},{"url":"bp0.blogger.com","hosted_by":"Google Inc.","green":true,"hosted_by_id":595,"modified":"2025-01-06T01:32:56.804433"},{"url":"ibb.co","hosted_by":null,"green":false,"hosted_by_id":null,"modified":"2025-01-06T01:32:57.121766"},{"url":"politico.com","hosted_by":"Amazon Web Services","green":true,"hosted_by_id":697,"modified":"2025-01-06T01:32:57.187925"},{"url":"behance.net","hosted_by":null,"green":false,"hosted_by_id":null,"modified":"2025-01-06T01:32:57.507165"},{"url":"frontiersin.org","hosted_by":"Microsoft Azure","green":true,"hosted_by_id":1091,"modified":"2025-01-06T01:32:57.550244"},{"url":"jpost.com","hosted_by":"Google Inc.","green":true,"hosted_by_id":595,"modified":"2025-01-06T01:32:57.613980"},{"url":"timeout.com","hosted_by":null,"green":false,"hosted_by_id":null,"modified":"2025-01-06T01:32:57.641344"},{"url":"depositfiles.com","hosted_by":null,"green":false,"hosted_by_id":null,"modified":"2025-01-06T01:32:58.215530"}],"greenDomains":195,"totalSites":500}